passwordsgo/__init__.py
passwordsgo/functions.py
passwordsgo/interface.py
passwordsgo/pysecret.py
passwordsgo-4.1.7.dist-info/METADATA
passwordsgo-4.1.7.dist-info/WHEEL
passwordsgo-4.1.7.dist-info/entry_points.txt
passwordsgo-4.1.7.dist-info/top_level.txt
passwordsgo-4.1.7.dist-info/RECORD
