Metadata-Version: 2.1
Name: passwordsgo
Version: 4.1.7
Summary: A Highly Secure Quantum Safe password management tool done as student project in cryptography.
Home-page: https://github.com/Anish-M-code/PyPass
Author: Anish M
Author-email: aneesh25861@gmail.com
License: GPLv3+
Keywords: Password manager,cryptography,student project
Platform: UNKNOWN
Classifier: Development Status :: 5 - Production/Stable
Classifier: Programming Language :: Python
Classifier: Topic :: Security :: Cryptography
Classifier: Topic :: Software Development :: Libraries :: Python Modules
Classifier: License :: OSI Approved :: GNU General Public License v3 or later (GPLv3+)
Classifier: Intended Audience :: End Users/Desktop
Classifier: Intended Audience :: Developers
Classifier: Operating System :: OS Independent
